okdmr/kaitai/etsi/__init__.py
okdmr/kaitai/etsi/dmr_csbk.ksy
okdmr/kaitai/etsi/dmr_csbk.py
okdmr/kaitai/etsi/dmr_data.ksy
okdmr/kaitai/etsi/dmr_data.py
okdmr/kaitai/etsi/dmr_data_header.ksy
okdmr/kaitai/etsi/dmr_data_header.py
okdmr/kaitai/etsi/dmr_ip_udp.ksy
okdmr/kaitai/etsi/dmr_ip_udp.py
okdmr/kaitai/etsi/full_link_control.ksy
okdmr/kaitai/etsi/full_link_control.py
okdmr/kaitai/homebrew/__init__.py
okdmr/kaitai/homebrew/homebrew2015.ksy
okdmr/kaitai/homebrew/homebrew2015.py
okdmr/kaitai/homebrew/mmdvm2020.ksy
okdmr/kaitai/homebrew/mmdvm2020.py
okdmr/kaitai/hytera/__init__.py
okdmr/kaitai/hytera/data_delivery_states.ksy
okdmr/kaitai/hytera/data_delivery_states.py
okdmr/kaitai/hytera/data_transmit_protocol.ksy
okdmr/kaitai/hytera/data_transmit_protocol.py
okdmr/kaitai/hytera/datetimestring.ksy
okdmr/kaitai/hytera/datetimestring.py
okdmr/kaitai/hytera/gpsdata.ksy
okdmr/kaitai/hytera/gpsdata.py
okdmr/kaitai/hytera/hytera_dmr_application_protocol.ksy
okdmr/kaitai/hytera/hytera_dmr_application_protocol.py
okdmr/kaitai/hytera/hytera_radio_network_protocol.ksy
okdmr/kaitai/hytera/hytera_radio_network_protocol.py
okdmr/kaitai/hytera/hytera_simple_transport_reliability_protocol.ksy
okdmr/kaitai/hytera/hytera_simple_transport_reliability_protocol.py
okdmr/kaitai/hytera/intervalstring.ksy
okdmr/kaitai/hytera/intervalstring.py
okdmr/kaitai/hytera/ip_site_connect_heartbeat.ksy
okdmr/kaitai/hytera/ip_site_connect_heartbeat.py
okdmr/kaitai/hytera/ip_site_connect_protocol.ksy
okdmr/kaitai/hytera/ip_site_connect_protocol.py
okdmr/kaitai/hytera/location_protocol.ksy
okdmr/kaitai/hytera/location_protocol.py
okdmr/kaitai/hytera/radio_control_protocol.ksy
okdmr/kaitai/hytera/radio_control_protocol.py
okdmr/kaitai/hytera/radio_id.ksy
okdmr/kaitai/hytera/radio_id.py
okdmr/kaitai/hytera/radio_ip.ksy
okdmr/kaitai/hytera/radio_ip.py
okdmr/kaitai/hytera/radio_registration_service.ksy
okdmr/kaitai/hytera/radio_registration_service.py
okdmr/kaitai/hytera/real_time_transport_protocol.ksy
dmr_kaitai-1.1.2.dist-info/METADATA
dmr_kaitai-1.1.2.dist-info/WHEEL
dmr_kaitai-1.1.2.dist-info/entry_points.txt
dmr_kaitai-1.1.2.dist-info/licenses/LICENSE
dmr_kaitai-1.1.2.dist-info/licenses/NOTICE
dmr_kaitai-1.1.2.dist-info/RECORD
