Metadata-Version: 2.4
Name: dmr-kaitai
Version: 1.1.2
Summary: Various DMR related protocols implemented with kaitai-first approach
Project-URL: repository, https://github.com/OK-DMR/dmr-kaitai
Author-email: Marek Sebera <marek.sebera@gmail.com>
License: AGPL-3.0
License-File: LICENSE
License-File: NOTICE
Keywords: dmr,etsi,ham,homebrew,hytera,kaitai,mmdvm,motorola,radio
Classifier: Development Status :: 5 - Production/Stable
Classifier: Environment :: Console
Classifier: Framework :: Pytest
Classifier: Intended Audience :: Telecommunications Industry
Classifier: License :: OSI Approved :: GNU Affero General Public License v3 or later (AGPLv3+)
Classifier: Natural Language :: English
Classifier: Operating System :: POSIX :: Linux
Classifier: Programming Language :: Python :: 3.8
Classifier: Topic :: Communications :: Ham Radio
Classifier: Topic :: Software Development :: Libraries
Classifier: Typing :: Typed
Requires-Python: >=3.8
Requires-Dist: kaitaistruct>=0.10
Provides-Extra: pre-commit
Requires-Dist: pre-commit>=3.0.0; extra == 'pre-commit'
Provides-Extra: test
Requires-Dist: black; extra == 'test'
Requires-Dist: coverage>=7.4.0; extra == 'test'
Requires-Dist: pre-commit; extra == 'test'
Requires-Dist: pytest-cov>=4.1.0; extra == 'test'
Requires-Dist: pytest>=8.1.1; extra == 'test'
